tuatara/config.py
tuatara/cover_art.py
tuatara/cover_art_fetcher.py
tuatara/image_utils.py
tuatara/interface.py
tuatara/main.py
tuatara/player.py
tuatara/playlist.py
tuatara/playlist_entry.py
tuatara/sanitize.py
tuatara/settings.py
tuatara-0.6.2.dist-info/METADATA
tuatara-0.6.2.dist-info/WHEEL
tuatara-0.6.2.dist-info/entry_points.txt
tuatara-0.6.2.dist-info/licenses/LICENSE.txt
tuatara-0.6.2.dist-info/RECORD
