Metadata-Version: 2.4
Name: tuatara
Version: 0.6.2
Summary: Tuatara is a text-mode music player.
License: GPL-3.0-or-later
License-File: LICENSE.txt
Keywords: music,media,player
Author: Bill Nottingham
Author-email: notting@splat.cc
Requires-Python: >=3.11,<3.15
Classifier: License :: OSI Approved :: GNU General Public License v3 or later (GPLv3+)
Classifier: Programming Language :: Python :: 3
Classifier: Programming Language :: Python :: 3.11
Classifier: Programming Language :: Python :: 3.12
Classifier: Programming Language :: Python :: 3.13
Classifier: Programming Language :: Python :: 3.14
Classifier: Topic :: Multimedia :: Sound/Audio :: Players
Classifier: Topic :: Multimedia :: Sound/Audio :: Players :: MP3
Requires-Dist: blessed (>=1.21.0,<2.0.0)
Requires-Dist: m3u8 (>=6.0.0,<7.0.0)
Requires-Dist: pillow (>=11.3.0,<12.0.0)
Requires-Dist: pygobject (>=3.46.0,<4.0.0)
Requires-Dist: urllib3 (>=2.1.0,<3.0.0)
Project-URL: Repository, https://github.com/wenottingham/tuatara
